simplesearch/__init__.py
simplesearch/_utils.py
simplesearch/db.py
simplesearch/db_helper.py
simplesearch/index.py
simplesearch/readers.py
simplesearch/search.py
simplesearch-0.0.1.dist-info/LICENSE
simplesearch-0.0.1.dist-info/METADATA
simplesearch-0.0.1.dist-info/WHEEL
simplesearch-0.0.1.dist-info/top_level.txt
simplesearch-0.0.1.dist-info/RECORD
